{
  "required": true,
  "minVersion": "0.8",
  "package": "dev.dubhe.gugle.carpet.mixin",
  "compatibilityLevel": "JAVA_17",
  "mixins": [
    "AbstractContainerMenuAccessor",
    "AbstractContainerMenuMixin",
    "ActionAccessor",
    "APAccessor",
    "AxeItemMixin",
    "ChestMenuMixin",
    "CommandsMixin",
    "EntityInvoker",
    "FenceGateBlockMixin",
    "FishingHookMixin",
    "ItemFrameMixin",
    "ItemStackMixin",
    "PlayerAccessor",
    "PlayerCommandMixin",
    "PlayerMixin",
    "ServerGamePacketListenerImplMixin",
    "ServerLevelMixin",
    "ServerPlaceRecipeMixin",
    "SignBlockMixin",
    "SlotMixin"
  ],
  "server": [
  ],
  "client": [
  ],
  "injectors": {
    "defaultRequire": 1
  }
}
